AUTHORS
CHANGELOG.rst
LICENSE
README.rst
docs/_static/runtimes.png
mdbenchmark/__init__.py
mdbenchmark/__main__.py
mdbenchmark/__version__.py
mdbenchmark/cli/__init__.py
mdbenchmark/cli/analyze.py
mdbenchmark/cli/commands.py
mdbenchmark/cli/generate.py
mdbenchmark/cli/options.py
mdbenchmark/cli/plot.py
mdbenchmark/cli/submit.py
mdbenchmark/cli/validators.py
mdbenchmark/console.py
mdbenchmark/ext/__init__.py
mdbenchmark/ext/click_test.py
mdbenchmark/math.py
mdbenchmark/mdengines/__init__.py
mdbenchmark/mdengines/gromacs.py
mdbenchmark/mdengines/namd.py
mdbenchmark/mdengines/utils.py
mdbenchmark/migrations/__init__.py
mdbenchmark/migrations/mds_to_dtr.py
mdbenchmark/models.py
mdbenchmark/templates/cobra
mdbenchmark/templates/draco
mdbenchmark/templates/hydra
mdbenchmark/tests/__init__.py
mdbenchmark/tests/conftest.py
mdbenchmark/tests/data/analyze-files-gromacs/1/.datreant/categories.json
mdbenchmark/tests/data/analyze-files-gromacs/1/bench.log
mdbenchmark/tests/data/analyze-files-gromacs/2/.datreant/categories.json
mdbenchmark/tests/data/analyze-files-gromacs/2/bench.log
mdbenchmark/tests/data/analyze-files-gromacs/3/.datreant/categories.json
mdbenchmark/tests/data/analyze-files-gromacs/3/bench.log
mdbenchmark/tests/data/analyze-files-gromacs/4/.datreant/categories.json
mdbenchmark/tests/data/analyze-files-gromacs/4/bench.log
mdbenchmark/tests/data/analyze-files-gromacs/5/.datreant/categories.json
mdbenchmark/tests/data/analyze-files-gromacs/5/bench.log
mdbenchmark/tests/data/analyze-files-gromacs-consolidated.csv
mdbenchmark/tests/data/analyze-files-gromacs-one-unstarted/1/.datreant/categories.json
mdbenchmark/tests/data/analyze-files-gromacs-one-unstarted/1/bench.log
mdbenchmark/tests/data/analyze-files-gromacs-one-unstarted/2/.datreant/categories.json
mdbenchmark/tests/data/analyze-files-gromacs-one-unstarted/2/bench.log
mdbenchmark/tests/data/analyze-files-gromacs-one-unstarted/3/.datreant/categories.json
mdbenchmark-3.0.1.dist-info/entry_points.txt
mdbenchmark-3.0.1.dist-info/LICENSE
mdbenchmark-3.0.1.dist-info/WHEEL
mdbenchmark-3.0.1.dist-info/METADATA
mdbenchmark-3.0.1.dist-info/RECORD
