Metadata-Version: 2.1
Name: mdbenchmark
Version: 3.0.1
Summary: Quickly generate, start and analyze benchmarks for your molecular dynamics simulations.
Home-page: https://mdbenchmark.org
License: GPL-3.0
Keywords: benchmark,molecular dynamics,simulations,gromacs,namd
Author: Max Linke
Requires-Python: >=3.6,<4.0
Classifier: Development Status :: 5 - Production/Stable
Classifier: Environment :: Console
Classifier: Intended Audience :: Science/Research
Classifier: License :: OSI Approved :: GNU General Public License (GPL)
Classifier: License :: OSI Approved :: GNU General Public License v3 (GPLv3)
Classifier: Operating System :: MacOS :: MacOS X
Classifier: Operating System :: POSIX
Classifier: Programming Language :: Python
Classifier: Programming Language :: Python :: 3
Classifier: Programming Language :: Python :: 3.6
Classifier: Programming Language :: Python :: 3.7
Classifier: Programming Language :: Python :: 3.8
Classifier: Programming Language :: Python :: 3.9
Classifier: Topic :: Scientific/Engineering
Classifier: Topic :: Scientific/Engineering :: Bio-Informatics
Classifier: Topic :: Scientific/Engineering :: Chemistry
Classifier: Topic :: Scientific/Engineering :: Physics
Classifier: Topic :: System :: Benchmark
Provides-Extra: docs
Requires-Dist: Sphinx (>=1,<2); extra == "docs"
Requires-Dist: click (>=6.7)
Requires-Dist: datreant (>=1.0,<2.0)
Requires-Dist: jinja2 (>=2.10,<3.0)
Requires-Dist: matplotlib (>=2)
Requires-Dist: numpy (>=1.15)
Requires-Dist: pandas (>=0.24)
Requires-Dist: psutil (>=5.7.0,<6.0.0)
Requires-Dist: python-levenshtein (>=0.12.0,<0.13.0)
Requires-Dist: sphinx-autobuild (>=0.7.1,<0.8.0); extra == "docs"
Requires-Dist: sphinx-click (>=2.3,<3.0); extra == "docs"
Requires-Dist: tabulate (>=0.8.5,<0.9.0)
Requires-Dist: xdg (>=1,<2)
Project-URL: Documentation, https://docs.mdbenchmark.org
Project-URL: Repository, https://github.com/bio-phys/mdbenchmark
